Disbot/__init__.py
Disbot/cli.py
Disbot/subcommands/__init__.py
Disbot/subcommands/commands.py
Disbot/template/Main.py
Disbot/template/README.py
Disbot/template/__init__.py
Disbot/template/_constants.py
Disbot/template/gitignore.py
Disbot/template/secret.py
Disbot/template/settings.py
Disbot/template/Cogs/Base.py
Disbot/template/Cogs/Errors.py
Disbot/template/Cogs/General.py
Disbot/template/Cogs/__init__.py
Disbot/template/Embeds/GeneralEmbed.py
Disbot/template/Embeds/__init__.py
DisBot-1.0.dist-info/METADATA
DisBot-1.0.dist-info/WHEEL
DisBot-1.0.dist-info/entry_points.txt
DisBot-1.0.dist-info/top_level.txt
DisBot-1.0.dist-info/RECORD
