Metadata-Version: 2.1
Name: DisBot
Version: 1.0
Summary: Tool to create a quick new discord.py bot
Home-page: https://github.com/GSri30/Disbot
Author: Sri Harsha G
Author-email: sri_3007@hotmail.com
License: MIT
Download-URL: https://pypi.org/project/DisBot
Keywords: discord.py,discord template,discord bot template,Disbot
Platform: UNKNOWN
Requires-Dist: click
Requires-Dist: python-dotenv
Requires-Dist: discord.py
